SchemGenerator/SchemGenerator.py
SchemGenerator/__init__.py
schemgenerator-1.0.6.dist-info/licenses/LICENSE
schemgenerator-1.0.6.dist-info/METADATA
schemgenerator-1.0.6.dist-info/WHEEL
schemgenerator-1.0.6.dist-info/top_level.txt
schemgenerator-1.0.6.dist-info/RECORD
