Metadata-Version: 2.4
Name: SchemGenerator
Version: 1.0.6
Summary: A Package for creating minecraft schematics
Home-page: https://github.com/TorbTorb/SchemGenerator
Author: Torb
Project-URL: Bug Tracker, https://github.com/TorbTorb/SchemGenerator/issues
Project-URL: repository, https://github.com/TorbTorb/SchemGenerator/issues
Classifier: Programming Language :: Python :: 3
Classifier: Intended Audience :: Education
Classifier: Intended Audience :: Developers
Classifier: Operating System :: OS Independent
Requires-Python: >=3.10
License-File: LICENSE
Requires-Dist: NBT
Dynamic: author
Dynamic: classifier
Dynamic: description
Dynamic: description-content-type
Dynamic: home-page
Dynamic: license-file
Dynamic: project-url
Dynamic: requires-dist
Dynamic: requires-python
Dynamic: summary
